gatb/core.so
gatb/plot_graph.py
gatb/VERSION
gatb/__init__.py
gatb/.libs/libz-a147dcb0.so.1.2.3
gatb/tests/test_package.py
gatb/tests/__init__.py
gatb/tests/test_bank.py
gatb/tests/test_graph.py
gatb/tests/db/reads3.fa.gz
gatb/tests/db/reads1.fa
gatb/tests/db/microsnp.fa
gatb/tests/db/reads1.fa.gz
gatb/tests/db/sample.fastq.gz
gatb/tests/db/sample1.fa
gatb/tests/db/reads1_list_ids.txt
gatb/tests/db/sample2.fa
gatb/tests/db/query.fa
gatb/tests/db/query.fa.gz
gatb/tests/db/celegans_reads.h5
gatb/tests/db/reads2.fa
gatb/tests/db/sample1.fa.gz
gatb/tests/db/album.txt
gatb/tests/db/sample.fastq
pyGATB-0.1.2.data/data/LICENSE
pyGATB-0.1.2.dist-info/RECORD
pyGATB-0.1.2.dist-info/METADATA
pyGATB-0.1.2.dist-info/WHEEL
pyGATB-0.1.2.dist-info/top_level.txt
pyGATB-0.1.2.dist-info/DESCRIPTION.rst
pyGATB-0.1.2.dist-info/metadata.json
